ptydevopsapi/__init__.py
ptydevopsapi/ptydevopsapi.py
ptydevopsapi-1.0.3.dist-info/DESCRIPTION.rst
ptydevopsapi-1.0.3.dist-info/METADATA
ptydevopsapi-1.0.3.dist-info/RECORD
ptydevopsapi-1.0.3.dist-info/WHEEL
ptydevopsapi-1.0.3.dist-info/metadata.json
ptydevopsapi-1.0.3.dist-info/top_level.txt
